{
  "title": "File:General Keychain Dispenser.jpg",
  "ns": 6,
  "id": 1489,
  "slug": "File_General_Keychain_Dispenser.jpg",
  "latest_revision": {
    "id": 5976,
    "timestamp": "2024-02-08T21:52:10Z",
    "contributor": {
      "username": "Eric Ose",
      "ip": null,
      "id": 681
    },
    "comment": "The keychain dispenser that Linwood built. Part of the larger donation bin project.",
    "text": "The keychain dispenser that Linwood built. Part of the larger donation bin project.",
    "bytes": 83
  },
  "revision_count": 1,
  "first_revision_timestamp": "2024-02-08T21:52:10Z",
  "is_redirect": false
}